odmantic/__init__.py
odmantic/bson.py
odmantic/config.py
odmantic/engine.py
odmantic/exceptions.py
odmantic/fastapi.py
odmantic/field.py
odmantic/index.py
odmantic/model.py
odmantic/py.typed
odmantic/query.py
odmantic/reference.py
odmantic/session.py
odmantic/typing.py
odmantic/utils.py
odmantic-0.9.1.dist-info/LICENSE
odmantic-0.9.1.dist-info/WHEEL
odmantic-0.9.1.dist-info/METADATA
odmantic-0.9.1.dist-info/RECORD
