Metadata-Version: 2.1
Name: odmantic
Version: 0.9.1
Summary: ODMantic, an AsyncIO MongoDB Object Document Mapper for Python using type hints 
Keywords: mongodb,asyncio,types,pydantic,motor
Author-email: Arthur Pastel <arthur.pastel@gmail.com>
Requires-Python: >=3.7
Classifier: Intended Audience :: Information Technology
Classifier: Intended Audience :: System Administrators
Classifier: Intended Audience :: Developers
Classifier: Operating System :: OS Independent
Classifier: Topic :: Internet
Classifier: Topic :: Database
Classifier: Topic :: Database :: Front-Ends
Classifier: Topic :: Software Development :: Object Brokering
Classifier: Topic :: Software Development :: Libraries :: Python Modules
Classifier: Topic :: Software Development :: Libraries
Classifier: Topic :: Software Development
Classifier: Typing :: Typed
Classifier: Development Status :: 4 - Beta
Classifier: Framework :: AsyncIO
Classifier: Environment :: Web Environment
Classifier: License :: OSI Approved :: ISC License (ISCL)
Classifier: Programming Language :: Python :: Implementation :: CPython
Classifier: Programming Language :: Python :: 3 :: Only
Classifier: Programming Language :: Python :: 3.7
Classifier: Programming Language :: Python :: 3.8
Classifier: Programming Language :: Python :: 3.9
Classifier: Programming Language :: Python :: 3.10
Classifier: Programming Language :: Python :: 3
Classifier: Programming Language :: Python
Requires-Dist: pydantic >=1.6.2,!=1.7,!=1.7.1,!=1.7.2,!=1.7.3,!=1.8,!=1.8.1
Requires-Dist: importlib-metadata >=1,<5; python_version<'3.8'
Requires-Dist: typing-extensions >= 4.2.0; python_version<'3.11'
Requires-Dist: motor >=2.1.0,<3.2.0
Requires-Dist: pymongo >=3.11.0,<5.0.0
Requires-Dist: ipython ~= 7.16.1 ; extra == "dev"
Requires-Dist: pydocstyle[toml] ~= 6.1.1 ; extra == "doc"
Requires-Dist: mkdocs-material ~= 8.4.0 ; extra == "doc"
Requires-Dist: mkdocstrings[python] ~= 0.19.0 ; extra == "doc"
Requires-Dist: mkdocs-macros-plugin ~= 0.5.0 ; extra == "doc"
Requires-Dist: fastapi >=0.61.1 ; extra == "fastapi"
Requires-Dist: black ~= 22.3.0 ; extra == "test"
Requires-Dist: isort ~=5.8.0 ; extra == "test"
Requires-Dist: ruff ~= 0.0.137 ; extra == "test"
Requires-Dist: mypy ~= 0.961 ; extra == "test"
Requires-Dist: pytest ~= 7.0 ; extra == "test"
Requires-Dist: pytest-xdist ~= 2.1.0 ; extra == "test"
Requires-Dist: pytest-asyncio ~= 0.16.0 ; extra == "test"
Requires-Dist: pytest-sugar ~= 0.9.5 ; extra == "test"
Requires-Dist: async-asgi-testclient ~= 1.4.4 ; extra == "test"
Requires-Dist: asyncmock ~= 0.4.2 ; extra == "test"
Requires-Dist: coverage[toml] ~= 6.2 ; extra == "test"
Requires-Dist: pytz ~= 2022.1 ; extra == "test"
Requires-Dist: darglint ~= 1.8.1 ; extra == "test"
Requires-Dist: uvicorn ~= 0.17.0 ; extra == "test"
Requires-Dist: fastapi >=0.61.1,<0.69.0 ; extra == "test"
Requires-Dist: requests ~= 2.24.0 ; extra == "test"
Requires-Dist: typer ~= 0.4.1 ; extra == "test"
Requires-Dist: semver ~= 2.13.0 ; extra == "test"
Requires-Dist: types-pytz ~= 2022.1.1 ; extra == "test"
Project-URL: Documentation, https://art049.github.io/odmantic
Project-URL: Source, https://github.com/art049/odmantic
Provides-Extra: dev
Provides-Extra: doc
Provides-Extra: fastapi
Provides-Extra: test
